MANIFEST.in
README.md
setup.py
tcomapi/__init__.py
tcomapi.egg-info/PKG-INFO
tcomapi.egg-info/SOURCES.txt
tcomapi.egg-info/dependency_links.txt
tcomapi.egg-info/entry_points.txt
tcomapi.egg-info/requires.txt
tcomapi.egg-info/top_level.txt
tcomapi.egg-info/zip-safe
tcomapi/common/__init__.py
tcomapi/common/cli_validators.py
tcomapi/common/constants.py
tcomapi/common/correctors.py
tcomapi/common/data_file_helper.py
tcomapi/common/data_verification.py
tcomapi/common/db.py
tcomapi/common/excel.py
tcomapi/common/exceptions.py
tcomapi/common/javascript.py
tcomapi/common/parsers.py
tcomapi/common/ratelimit.py
tcomapi/common/unpacking.py
tcomapi/common/utils.py
tcomapi/dgov/__init__.py
tcomapi/dgov/api.py
tcomapi/dgov/async.py
tcomapi/kgd/__init__.py
tcomapi/kgd/__main__.py
tcomapi/kgd/api.py
tcomapi/kgd/cli.py
tcomapi/kgd/exceptions.py
tcomapi/kgd/request.xml
tcomapi/sgov/__init__.py
tcomapi/sgov/__main__.py
tcomapi/sgov/api.py
tcomapi/sgov/cli.py
tcomapi/utils/__init__.py