Metadata-Version: 2.1
Name: tcomapi
Version: 0.1.13
Summary: Bundle for getting open data from some KZ sites.
Home-page: https://github.com/elessarelfstone/tcomapi
Author: Dauren Sdykov
Author-email: elessarelfstone@mail.ru
License: MIT
Platform: UNKNOWN
Classifier: Programming Language :: Python :: 3.6
Classifier: License :: OSI Approved :: MIT License
Classifier: Operating System :: OS Independent
Classifier: Development Status :: 4 - Beta
Classifier: Environment :: No Input/Output (Daemon)
Classifier: Intended Audience :: System Administrators
Classifier: Natural Language :: English
Classifier: Topic :: Internet
Requires-Python: >=3.6.1
Provides-Extra: dev
